twopilabs/sense/scpidevice/__init__.py
twopilabs/sense/scpidevice/acquisition.py
twopilabs/sense/scpidevice/constants.py
twopilabs/sense/scpidevice/scpi_calc.py
twopilabs/sense/scpidevice/scpi_control.py
twopilabs/sense/scpidevice/scpi_core.py
twopilabs/sense/scpidevice/scpi_device.py
twopilabs/sense/scpidevice/scpi_initiate.py
twopilabs/sense/scpidevice/scpi_sense.py
twopilabs/sense/scpidevice/scpi_system.py
twopilabs/sense/scpidevice/scpi_trigger.py
twopilabs_sense_scpidevice-0.1.3.dist-info/licenses/LICENSE
twopilabs_sense_scpidevice-0.1.3.dist-info/METADATA
twopilabs_sense_scpidevice-0.1.3.dist-info/WHEEL
twopilabs_sense_scpidevice-0.1.3.dist-info/top_level.txt
twopilabs_sense_scpidevice-0.1.3.dist-info/RECORD
