Metadata-Version: 2.4
Name: twopilabs-sense-scpidevice
Version: 0.1.3
Summary: Base package for 2pi-Labs SENSE SCPI devices
Home-page: https://www.2pi-labs.com
Author: 2pi-Labs GmbH
Author-email: opensource@2pi-labs.com
License: LGPLv3
Classifier: License :: OSI Approved :: GNU Lesser General Public License v3 (LGPLv3)
Classifier: Programming Language :: Python :: 3
Requires-Python: >=3.10
License-File: LICENSE
Requires-Dist: numpy
Requires-Dist: twopilabs-utils-scpi
Dynamic: license-file
